TabLabels/__init__.py
TabLabels/oopTablabel.py
TabLabels/tabLabel.py
TabLabels-1.0.4.dist-info/METADATA
TabLabels-1.0.4.dist-info/WHEEL
TabLabels-1.0.4.dist-info/top_level.txt
TabLabels-1.0.4.dist-info/RECORD
